[
  {
    "public_id": "IMG20260707152023_uahvp4",
    "url": "https://res.cloudinary.com/tftagnuy/image/upload/v1783439093/IMG20260707152023_uahvp4.jpg",
    "width": 4096,
    "height": 3072,
    "created_at": "2026-07-07T15:44:53Z",
    "tags": [
      "day04",
      "kyrgyzstan-2026"
    ]
  },
  {
    "public_id": "IMG20260707115236_ope1bf",
    "url": "https://res.cloudinary.com/tftagnuy/image/upload/v1783439094/IMG20260707115236_ope1bf.jpg",
    "width": 4096,
    "height": 3072,
    "created_at": "2026-07-07T15:44:54Z",
    "tags": [
      "day04",
      "kyrgyzstan-2026"
    ]
  },
  {
    "public_id": "IMG20260707185135_curonf",
    "url": "https://res.cloudinary.com/tftagnuy/image/upload/v1783439095/IMG20260707185135_curonf.jpg",
    "width": 4096,
    "height": 3072,
    "created_at": "2026-07-07T15:44:55Z",
    "tags": [
      "day04",
      "kyrgyzstan-2026"
    ]
  },
  {
    "public_id": "IMG20260707133952_r9xppo",
    "url": "https://res.cloudinary.com/tftagnuy/image/upload/v1783439107/IMG20260707133952_r9xppo.jpg",
    "width": 4096,
    "height": 3072,
    "created_at": "2026-07-07T15:45:07Z",
    "tags": [
      "day04",
      "kyrgyzstan-2026"
    ]
  },
  {
    "public_id": "IMG20260707122036_g66kkm",
    "url": "https://res.cloudinary.com/tftagnuy/image/upload/v1783439107/IMG20260707122036_g66kkm.jpg",
    "width": 3072,
    "height": 4096,
    "created_at": "2026-07-07T15:45:07Z",
    "tags": [
      "day04",
      "kyrgyzstan-2026"
    ]
  },
  {
    "public_id": "IMG20260707113501_d19nyo",
    "url": "https://res.cloudinary.com/tftagnuy/image/upload/v1783439114/IMG20260707113501_d19nyo.jpg",
    "width": 3072,
    "height": 4096,
    "created_at": "2026-07-07T15:45:14Z",
    "tags": [
      "day04",
      "kyrgyzstan-2026"
    ]
  },
  {
    "public_id": "IMG20260707153207_swlibm",
    "url": "https://res.cloudinary.com/tftagnuy/image/upload/v1783439132/IMG20260707153207_swlibm.jpg",
    "width": 4096,
    "height": 3072,
    "created_at": "2026-07-07T15:45:32Z",
    "tags": [
      "day04",
      "kyrgyzstan-2026"
    ]
  },
  {
    "public_id": "IMG20260707150544_b2xvi1",
    "url": "https://res.cloudinary.com/tftagnuy/image/upload/v1783439135/IMG20260707150544_b2xvi1.jpg",
    "width": 4096,
    "height": 3072,
    "created_at": "2026-07-07T15:45:35Z",
    "tags": [
      "day04",
      "kyrgyzstan-2026"
    ]
  },
  {
    "public_id": "IMG20260707121057_b9oumd",
    "url": "https://res.cloudinary.com/tftagnuy/image/upload/v1783439135/IMG20260707121057_b9oumd.jpg",
    "width": 3072,
    "height": 4096,
    "created_at": "2026-07-07T15:45:35Z",
    "tags": [
      "day04",
      "kyrgyzstan-2026"
    ]
  },
  {
    "public_id": "IMG20260707151822_l3txyw",
    "url": "https://res.cloudinary.com/tftagnuy/image/upload/v1783439137/IMG20260707151822_l3txyw.jpg",
    "width": 4096,
    "height": 3072,
    "created_at": "2026-07-07T15:45:37Z",
    "tags": [
      "day04",
      "kyrgyzstan-2026"
    ]
  },
  {
    "public_id": "IMG20260707144053_gsufnu",
    "url": "https://res.cloudinary.com/tftagnuy/image/upload/v1783439146/IMG20260707144053_gsufnu.jpg",
    "width": 4096,
    "height": 3072,
    "created_at": "2026-07-07T15:45:46Z",
    "tags": [
      "day04",
      "kyrgyzstan-2026"
    ]
  },
  {
    "public_id": "IMG_20260707_215132_282_d0mqan",
    "url": "https://res.cloudinary.com/tftagnuy/image/upload/v1783439589/IMG_20260707_215132_282_d0mqan.jpg",
    "width": 960,
    "height": 1280,
    "created_at": "2026-07-07T15:53:09Z",
    "tags": [
      "day04",
      "kyrgyzstan-2026"
    ]
  },
  {
    "public_id": "IMG_20260707_215224_386_ylq6xi",
    "url": "https://res.cloudinary.com/tftagnuy/image/upload/v1783439590/IMG_20260707_215224_386_ylq6xi.jpg",
    "width": 960,
    "height": 1280,
    "created_at": "2026-07-07T15:53:10Z",
    "tags": [
      "day04",
      "kyrgyzstan-2026"
    ]
  },
  {
    "public_id": "IMG_20260707_215345_904_beowfa",
    "url": "https://res.cloudinary.com/tftagnuy/image/upload/v1783439660/IMG_20260707_215345_904_beowfa.jpg",
    "width": 960,
    "height": 1280,
    "created_at": "2026-07-07T15:54:20Z",
    "tags": [
      "day04",
      "kyrgyzstan-2026"
    ]
  },
  {
    "public_id": "IMG_20260707_215345_948_kknvim",
    "url": "https://res.cloudinary.com/tftagnuy/image/upload/v1783439661/IMG_20260707_215345_948_kknvim.jpg",
    "width": 960,
    "height": 1280,
    "created_at": "2026-07-07T15:54:21Z",
    "tags": [
      "day04",
      "kyrgyzstan-2026"
    ]
  },
  {
    "public_id": "IMG_20260707_215350_326_a0grqo",
    "url": "https://res.cloudinary.com/tftagnuy/image/upload/v1783439662/IMG_20260707_215350_326_a0grqo.jpg",
    "width": 1280,
    "height": 960,
    "created_at": "2026-07-07T15:54:22Z",
    "tags": [
      "day04",
      "kyrgyzstan-2026"
    ]
  },
  {
    "public_id": "IMG_20260707_215356_444_oevpsk",
    "url": "https://res.cloudinary.com/tftagnuy/image/upload/v1783439668/IMG_20260707_215356_444_oevpsk.jpg",
    "width": 960,
    "height": 1280,
    "created_at": "2026-07-07T15:54:28Z",
    "tags": [
      "day04",
      "kyrgyzstan-2026"
    ]
  },
  {
    "public_id": "IMG_20260707_215356_917_oy7kyl",
    "url": "https://res.cloudinary.com/tftagnuy/image/upload/v1783439669/IMG_20260707_215356_917_oy7kyl.jpg",
    "width": 960,
    "height": 1280,
    "created_at": "2026-07-07T15:54:29Z",
    "tags": [
      "day04",
      "kyrgyzstan-2026"
    ]
  }
]